latdraw/__init__.py
latdraw/interfaces.py
latdraw/latdraw.py
latdraw/lattice.py
latdraw/optics.py
latdraw/plot.py
latdraw-0.2.0.dist-info/METADATA
latdraw-0.2.0.dist-info/WHEEL
latdraw-0.2.0.dist-info/licenses/LICENSE
latdraw-0.2.0.dist-info/RECORD
