Metadata-Version: 2.4
Name: latdraw
Version: 0.2.0
Summary: Draw Accelerator lattices in Python.
License-File: LICENSE
Classifier: Development Status :: 2 - Pre-Alpha
Classifier: Intended Audience :: Developers
Classifier: License :: OSI Approved :: MIT License
Classifier: Natural Language :: English
Classifier: Programming Language :: Python :: 3
Classifier: Programming Language :: Python :: 3.13
Requires-Python: >=3.13
Requires-Dist: mad8-pandas>=1.1.1
Requires-Dist: matplotlib>=3.10.6
Requires-Dist: tfs-pandas>=4.0.0
